.gitignore
.landscape.yml
CHANGES.txt
LICENSE
MANIFEST.in
README.rst
docs_requirements.txt
setup.py
docs/Makefile
docs/make.bat
docs/source/conf.py
docs/source/index.rst
docs/source/remote_multicommand.rst
remote_multicommand/__init__.py
remote_multicommand/remote_multicommand.py
remote_multicommand.egg-info/PKG-INFO
remote_multicommand.egg-info/SOURCES.txt
remote_multicommand.egg-info/dependency_links.txt
remote_multicommand.egg-info/requires.txt
remote_multicommand.egg-info/top_level.txt