Metadata-Version: 1.1
Name: remote_multicommand
Version: 0.1.3
Summary: Provides execution of multiple commands in multiple servers in parallel (multiple processes)
Home-page: https://github.com/jonDel/remote_multicommand
Author: Jonatan Dellagostin
Author-email: jdellagostin@gmail.com
License: GPLv3
Keywords: ssh secure multi multi-processing parallel multiprocessing shell remote paramiko
Platform: UNKNOWN
Classifier: Development Status :: 3 - Alpha
Classifier: License :: OSI Approved :: GNU General Public License v3 (GPLv3)
Classifier: Programming Language :: Python :: 2.6
Classifier: Programming Language :: Python :: 2.7
Classifier: Topic :: System :: Networking
Classifier: Topic :: System :: Systems Administration
Classifier: Topic :: System :: Shells
Classifier: Topic :: System :: Hardware :: Symmetric Multi-processing
